{"vhash": "dd0928e9fc8d2e426c6e2c6da9b24512", "submission_names": ["0364f1a3fddde8ceb096817fb59888dd.apk", "1e0b412576eeb879aba0887a9022f797ea8d7815.apk", "243721649740.apk"], "scan_date": "2021-04-15 04:34:40", "first_seen": "2019-10-05 05:11:32", "times_submitted": 20, "additional_info": {"magic": "Zip archive data", "sigcheck": {}, "exiftool": {"ZipRequiredVersion": "0", "MIMEType": "application/zip", "ZipCRC": "0xfd2e9d3f", "FileType": "ZIP", "ZipCompression": "Deflated", "ZipUncompressedSize": "22164", "ZipCompressedSize": "5305", "FileTypeExtension": "zip", "ZipFileName": "AndroidManifest.xml", "ZipBitFlag": "0", "ZipModifyDate": "1980:00:00 00:00:00"}, "trid": "Android Package (57.0%)\nJava Archive (20.0%)\nSweet Home 3D design (generic) (15.5%)\nZIP compressed archive (5.9%)\nPrintFox/Pagefox bitmap (640x800) (1.4%)", "positives_delta": -1, "compressedview": {"highest_datetime": "1980-00-00 00:00:00", "tags": [], "lowest_datetime": "1980-00-00 00:00:00", "num_children": 1019, "extensions": {"xml": 235, "dex": 1, "MF": 1, "RSA": 1, "jpg": 9, "SF": 1, "ttf": 1, "png": 692}, "file_types": {"XML": 233, "unknown": 65, "DEX": 1, "JPG": 9, "PNG": 692}, "type": "APK", "children": [{"size": 22164, "sha256": "56258697ee0673f73a10de63ae1d11ffc17b87e7eaad82c0f9b30c03d144c87b", "type": "XML", "filename": "AndroidManifest.xml", "datetime": "1980-00-00 00:00:00"}, {"size": 1247, "sha256": "60ca8439fce14ffe80553d896219da6c7c86d6be2ff4218956bbd58a37cb9fa2", "type": "unknown", "filename": "META-INF/CERT.RSA", "datetime": "1980-00-00 00:00:00"}, {"size": 97114, "sha256": "e7ccc10009caa5c521efe5a8743a2185e826ed88c17c6e8c47ed8437de6ea906", "type": "unknown", "filename": "META-INF/CERT.SF", "datetime": "1980-00-00 00:00:00"}, {"size": 97071, "sha256": "d4a40ede8039bdedb9935625fdd64462546f14593c74da3ddc9b987114da67f9", "type": "unknown", "filename": "META-INF/MANIFEST.MF", "datetime": "1980-00-00 00:00:00"}, {"detection_ratio": [0, 76], "filename": "assets/BRoya.ttf", "datetime": "1980-00-00 00:00:00", "sha256": "362b518821063a5194221a7e0b3309b09b82fa50ad26f2761d07efb2ca643482", "type": "unknown", "size": 100576}, {"size": 81, "sha256": "efa9478e488c5a1fa1e9d3c3e60dc8fd7a75429b270c2d425a6cb0df1ad9fc31", "type": "unknown", "filename": "assets/md_base", "datetime": "1980-00-00 00:00:00"}, {"size": 81, "sha256": "efa9478e488c5a1fa1e9d3c3e60dc8fd7a75429b270c2d425a6cb0df1ad9fc31", "type": "unknown", "filename": "assets/md_book", "datetime": "1980-00-00 00:00:00"}, {"size": 4079, "sha256": "bcfb7f3d7f424f5d593d44d7eadfe00f5c73ce35c7b312819d73fecfeacb5f16", "type": "unknown", "filename": "assets/md_book_button", "datetime": "1980-00-00 00:00:00"}, {"size": 4079, "sha256": "bcfb7f3d7f424f5d593d44d7eadfe00f5c73ce35c7b312819d73fecfeacb5f16", "type": "unknown", "filename": "assets/md_book_card", "datetime": "1980-00-00 00:00:00"}, {"size": 4079, "sha256": "bcfb7f3d7f424f5d593d44d7eadfe00f5c73ce35c7b312819d73fecfeacb5f16", "type": "unknown", "filename": "assets/md_book_database", "datetime": "1980-00-00 00:00:00"}, {"size": 4079, "sha256": "bcfb7f3d7f424f5d593d44d7eadfe00f5c73ce35c7b312819d73fecfeacb5f16", "type": "unknown", "filename": "assets/md_book_fab", "datetime": "1980-00-00 00:00:00"}, {"size": 4079, "sha256": "bcfb7f3d7f424f5d593d44d7eadfe00f5c73ce35c7b312819d73fecfeacb5f16", "type": "unknown", "filename": "assets/md_book_head", "datetime": "1980-00-00 00:00:00"}, {"size": 4079, "sha256": "bcfb7f3d7f424f5d593d44d7eadfe00f5c73ce35c7b312819d73fecfeacb5f16", "type": "unknown", "filename": "assets/md_book_layout", "datetime": "1980-00-00 00:00:00"}, {"size": 4079, "sha256": "bcfb7f3d7f424f5d593d44d7eadfe00f5c73ce35c7b312819d73fecfeacb5f16", "type": "unknown", "filename": "assets/md_book_list", "datetime": "1980-00-00 00:00:00"}, {"size": 4079, "sha256": "bcfb7f3d7f424f5d593d44d7eadfe00f5c73ce35c7b312819d73fecfeacb5f16", "type": "unknown", "filename": "assets/md_book_number", "datetime": "1980-00-00 00:00:00"}, {"size": 4079, "sha256": "bcfb7f3d7f424f5d593d44d7eadfe00f5c73ce35c7b312819d73fecfeacb5f16", "type": "unknown", "filename": "assets/md_book_pic", "datetime": "1980-00-00 00:00:00"}, {"size": 4079, "sha256": "bcfb7f3d7f424f5d593d44d7eadfe00f5c73ce35c7b312819d73fecfeacb5f16", "type": "unknown", "filename": "assets/md_book_text", "datetime": "1980-00-00 00:00:00"}, {"size": 4079, "sha256": "bcfb7f3d7f424f5d593d44d7eadfe00f5c73ce35c7b312819d73fecfeacb5f16", "type": "unknown", "filename": "assets/md_book_view", "datetime": "1980-00-00 00:00:00"}, {"size": 81, "sha256": "efa9478e488c5a1fa1e9d3c3e60dc8fd7a75429b270c2d425a6cb0df1ad9fc31", "type": "unknown", "filename": "assets/md_cant", "datetime": "1980-00-00 00:00:00"}, {"size": 81, "sha256": "efa9478e488c5a1fa1e9d3c3e60dc8fd7a75429b270c2d425a6cb0df1ad9fc31", "type": "unknown", "filename": "assets/md_cont", "datetime": "1980-00-00 00:00:00"}, {"size": 81, "sha256": "efa9478e488c5a1fa1e9d3c3e60dc8fd7a75429b270c2d425a6cb0df1ad9fc31", "type": "unknown", "filename": "assets/md_database", "datetime": "1980-00-00 00:00:00"}, {"size": 81, "sha256": "efa9478e488c5a1fa1e9d3c3e60dc8fd7a75429b270c2d425a6cb0df1ad9fc31", "type": "unknown", "filename": "assets/md_database_bace", "datetime": "1980-00-00 00:00:00"}, {"size": 81, "sha256": "efa9478e488c5a1fa1e9d3c3e60dc8fd7a75429b270c2d425a6cb0df1ad9fc31", "type": "unknown", "filename": "assets/md_database_back", "datetime": "1980-00-00 00:00:00"}, {"size": 81, "sha256": "efa9478e488c5a1fa1e9d3c3e60dc8fd7a75429b270c2d425a6cb0df1ad9fc31", "type": "unknown", "filename": "assets/md_database_call", "datetime": "1980-00-00 00:00:00"}, {"size": 81, "sha256": "efa9478e488c5a1fa1e9d3c3e60dc8fd7a75429b270c2d425a6cb0df1ad9fc31", "type": "unknown", "filename": "assets/md_database_current", "datetime": "1980-00-00 00:00:00"}, {"size": 81, "sha256": "efa9478e488c5a1fa1e9d3c3e60dc8fd7a75429b270c2d425a6cb0df1ad9fc31", "type": "unknown", "filename": "assets/md_database_end", "datetime": "1980-00-00 00:00:00"}, {"size": 81, "sha256": "efa9478e488c5a1fa1e9d3c3e60dc8fd7a75429b270c2d425a6cb0df1ad9fc31", "type": "unknown", "filename": "assets/md_database_face", "datetime": "1980-00-00 00:00:00"}, {"size": 81, "sha256": "efa9478e488c5a1fa1e9d3c3e60dc8fd7a75429b270c2d425a6cb0df1ad9fc31", "type": "unknown", "filename": "assets/md_database_full", "datetime": "1980-00-00 00:00:00"}, {"size": 81, "sha256": "efa9478e488c5a1fa1e9d3c3e60dc8fd7a75429b270c2d425a6cb0df1ad9fc31", "type": "unknown", "filename": "assets/md_database_list", "datetime": "1980-00-00 00:00:00"}, {"size": 81, "sha256": "efa9478e488c5a1fa1e9d3c3e60dc8fd7a75429b270c2d425a6cb0df1ad9fc31", "type": "unknown", "filename": "assets/md_database_list_view", "datetime": "1980-00-00 00:00:00"}, {"size": 81, "sha256": "efa9478e488c5a1fa1e9d3c3e60dc8fd7a75429b270c2d425a6cb0df1ad9fc31", "type": "unknown", "filename": "assets/md_database_listener", "datetime": "1980-00-00 00:00:00"}, {"size": 81, "sha256": "efa9478e488c5a1fa1e9d3c3e60dc8fd7a75429b270c2d425a6cb0df1ad9fc31", "type": "unknown", "filename": "assets/md_database_pull", "datetime": "1980-00-00 00:00:00"}, {"size": 81, "sha256": "efa9478e488c5a1fa1e9d3c3e60dc8fd7a75429b270c2d425a6cb0df1ad9fc31", "type": "unknown", "filename": "assets/md_database_sinc", "datetime": "1980-00-00 00:00:00"}, {"size": 81, "sha256": "efa9478e488c5a1fa1e9d3c3e60dc8fd7a75429b270c2d425a6cb0df1ad9fc31", "type": "unknown", "filename": "assets/md_database_stu", "datetime": "1980-00-00 00:00:00"}, {"size": 81, "sha256": "efa9478e488c5a1fa1e9d3c3e60dc8fd7a75429b270c2d425a6cb0df1ad9fc31", "type": "unknown", "filename": "assets/md_end", "datetime": "1980-00-00 00:00:00"}, {"size": 4079, "sha256": "bcfb7f3d7f424f5d593d44d7eadfe00f5c73ce35c7b312819d73fecfeacb5f16", "type": "unknown", "filename": "assets/md_filter", "datetime": "1980-00-00 00:00:00"}, {"size": 81, "sha256": "efa9478e488c5a1fa1e9d3c3e60dc8fd7a75429b270c2d425a6cb0df1ad9fc31", "type": "unknown", "filename": "assets/md_foider", "datetime": "1980-00-00 00:00:00"}, {"size": 81, "sha256": "efa9478e488c5a1fa1e9d3c3e60dc8fd7a75429b270c2d425a6cb0df1ad9fc31", "type": "unknown", "filename": "assets/md_fome", "datetime": "1980-00-00 00:00:00"}, {"size": 13238272, "sha256": "1238b2dc9bd4b8fde9e48414cc083318bf7b04746b3d4aa3ea71dd4733ce3825", "type": "unknown", "filename": "assets/md_font", "datetime": "1980-00-00 00:00:00"}, {"size": 81, "sha256": "efa9478e488c5a1fa1e9d3c3e60dc8fd7a75429b270c2d425a6cb0df1ad9fc31", "type": "unknown", "filename": "assets/md_font_back", "datetime": "1980-00-00 00:00:00"}, {"size": 4079, "sha256": "bcfb7f3d7f424f5d593d44d7eadfe00f5c73ce35c7b312819d73fecfeacb5f16", "type": "unknown", "filename": "assets/md_font_date", "datetime": "1980-00-00 00:00:00"}, {"size": 4079, "sha256": "bcfb7f3d7f424f5d593d44d7eadfe00f5c73ce35c7b312819d73fecfeacb5f16", "type": "unknown", "filename": "assets/md_font_list", "datetime": "1980-00-00 00:00:00"}, {"size": 81, "sha256": "efa9478e488c5a1fa1e9d3c3e60dc8fd7a75429b270c2d425a6cb0df1ad9fc31", "type": "unknown", "filename": "assets/md_font_view", "datetime": "1980-00-00 00:00:00"}, {"size": 81, "sha256": "efa9478e488c5a1fa1e9d3c3e60dc8fd7a75429b270c2d425a6cb0df1ad9fc31", "type": "unknown", "filename": "assets/md_frag", "datetime": "1980-00-00 00:00:00"}, {"size": 81, "sha256": "efa9478e488c5a1fa1e9d3c3e60dc8fd7a75429b270c2d425a6cb0df1ad9fc31", "type": "unknown", "filename": "assets/md_main", "datetime": "1980-00-00 00:00:00"}, {"size": 81, "sha256": "efa9478e488c5a1fa1e9d3c3e60dc8fd7a75429b270c2d425a6cb0df1ad9fc31", "type": "unknown", "filename": "assets/md_match", "datetime": "1980-00-00 00:00:00"}, {"size": 81, "sha256": "efa9478e488c5a1fa1e9d3c3e60dc8fd7a75429b270c2d425a6cb0df1ad9fc31", "type": "unknown", "filename": "assets/md_parrent", "datetime": "1980-00-00 00:00:00"}, {"size": 81, "sha256": "efa9478e488c5a1fa1e9d3c3e60dc8fd7a75429b270c2d425a6cb0df1ad9fc31", "type": "unknown", "filename": "assets/md_splash", "datetime": "1980-00-00 00:00:00"}, {"size": 81, "sha256": "efa9478e488c5a1fa1e9d3c3e60dc8fd7a75429b270c2d425a6cb0df1ad9fc31", "type": "unknown", "filename": "assets/md_start", "datetime": "1980-00-00 00:00:00"}, {"size": 81, "sha256": "efa9478e488c5a1fa1e9d3c3e60dc8fd7a75429b270c2d425a6cb0df1ad9fc31", "type": "unknown", "filename": "assets/md_sub", "datetime": "1980-00-00 00:00:00"}, {"size": 81, "sha256": "efa9478e488c5a1fa1e9d3c3e60dc8fd7a75429b270c2d425a6cb0df1ad9fc31", "type": "unknown", "filename": "assets/md_text", "datetime": "1980-00-00 00:00:00"}, {"size": 81, "sha256": "efa9478e488c5a1fa1e9d3c3e60dc8fd7a75429b270c2d425a6cb0df1ad9fc31", "type": "unknown", "filename": "assets/md_text_back", "datetime": "1980-00-00 00:00:00"}, {"size": 81, "sha256": "efa9478e488c5a1fa1e9d3c3e60dc8fd7a75429b270c2d425a6cb0df1ad9fc31", "type": "unknown", "filename": "assets/md_text_back_pull", "datetime": "1980-00-00 00:00:00"}, {"size": 81, "sha256": "efa9478e488c5a1fa1e9d3c3e60dc8fd7a75429b270c2d425a6cb0df1ad9fc31", "type": "unknown", "filename": "assets/md_text_last", "datetime": "1980-00-00 00:00:00"}, {"size": 81, "sha256": "efa9478e488c5a1fa1e9d3c3e60dc8fd7a75429b270c2d425a6cb0df1ad9fc31", "type": "unknown", "filename": "assets/md_text_layout", "datetime": "1980-00-00 00:00:00"}, {"size": 81, "sha256": "efa9478e488c5a1fa1e9d3c3e60dc8fd7a75429b270c2d425a6cb0df1ad9fc31", "type": "unknown", "filename": "assets/md_text_match", "datetime": "1980-00-00 00:00:00"}, {"size": 81, "sha256": "efa9478e488c5a1fa1e9d3c3e60dc8fd7a75429b270c2d425a6cb0df1ad9fc31", "type": "unknown", "filename": "assets/md_text_pull", "datetime": "1980-00-00 00:00:00"}, {"size": 81, "sha256": "efa9478e488c5a1fa1e9d3c3e60dc8fd7a75429b270c2d425a6cb0df1ad9fc31", "type": "unknown", "filename": "assets/md_text_st", "datetime": "1980-00-00 00:00:00"}, {"size": 81, "sha256": "efa9478e488c5a1fa1e9d3c3e60dc8fd7a75429b270c2d425a6cb0df1ad9fc31", "type": "unknown", "filename": "assets/md_text_view", "datetime": "1980-00-00 00:00:00"}, {"size": 81, "sha256": "efa9478e488c5a1fa1e9d3c3e60dc8fd7a75429b270c2d425a6cb0df1ad9fc31", "type": "unknown", "filename": "assets/md_text_warp", "datetime": "1980-00-00 00:00:00"}, {"size": 81, "sha256": "efa9478e488c5a1fa1e9d3c3e60dc8fd7a75429b270c2d425a6cb0df1ad9fc31", "type": "unknown", "filename": "assets/md_viewer", "datetime": "1980-00-00 00:00:00"}, {"size": 81, "sha256": "efa9478e488c5a1fa1e9d3c3e60dc8fd7a75429b270c2d425a6cb0df1ad9fc31", "type": "unknown", "filename": "assets/md_wrap", "datetime": "1980-00-00 00:00:00"}, {"detection_ratio": [0, 74], "filename": "build-data.properties", "datetime": "1980-00-00 00:00:00", "sha256": "0d3f70d64db5ad0316317132bd148f7c27c072a8959503edc729335f96895c7a", "type": "unknown", "size": 157}, {"detection_ratio": [17, 74], "filename": "classes.dex", "datetime": "1980-00-00 00:00:00", "sha256": "6c47c4aa0e677bb98c8391933f6840db7dedabc83c8efce1bc01c3f20c5f113b", "type": "DEX", "size": 5345832}, {"detection_ratio": [0, 74], "filename": "error_prone/Annotations.gwt.xml", "datetime": "1980-00-00 00:00:00", "sha256": "c118a3de9a4be1f5fa7bb5dc422d8367dd4765ded5d95c2f57419a3862a91bee", "type": "unknown", "size": 119}, {"detection_ratio": [0, 74], "filename": "jsr305_annotations/Jsr305_annotations.gwt.xml", "datetime": "1980-00-00 00:00:00", "sha256": "0215a446bddde28ed59ae7122f8f59472d4be649ac7b92d5f56488407b364f39", "type": "unknown", "size": 133}, {"detection_ratio": [0, 72], "filename": "protobuf.meta", "datetime": "1980-00-00 00:00:00", "sha256": "e0066945b03e99e0aa6559e2ed6d148a66ffbf0e6c39091be009d67c9ffcb5bb", "type": "unknown", "size": 158463}, {"detection_ratio": [0, 75], "filename": "res/anim/abc_fade_in.xml", "datetime": "1980-00-00 00:00:00", "sha256": "7980a2f9190b96ec3f349161b827f752eb64371a1c94abdec0c70e2f60eaf23a", "type": "XML", "size": 328}, {"detection_ratio": [0, 74], "filename": "res/anim/abc_fade_out.xml", "datetime": "1980-00-00 00:00:00", "sha256": "367adb7e7088e34e361e51b776c6327edb39b056c8cc52336e6082f339df1004", "type": "XML", "size": 328}, {"detection_ratio": [0, 73], "filename": "res/anim/abc_grow_fade_in_from_bottom.xml", "datetime": "1980-00-00 00:00:00", "sha256": "baa0f338009d25755fc2e182715a3c77f9f0dc711fca7237b32fe64fd7788111", "type": "XML", "size": 792}, {"detection_ratio": [0, 73], "filename": "res/anim/abc_popup_enter.xml", "datetime": "1980-00-00 00:00:00", "sha256": "c97c48dbf8fda6a4c5272e957f73b01c677be30c3cf467711e1af7fd63d7cffe", "type": "XML", "size": 444}, {"detection_ratio": [0, 73], "filename": "res/anim/abc_popup_exit.xml", "datetime": "1980-00-00 00:00:00", "sha256": "589f6ed0d86c780199734ca33fc0f4cc0226086534bff039fd2c79acaaeed13b", "type": "XML", "size": 444}, {"detection_ratio": [0, 73], "filename": "res/anim/abc_shrink_fade_out_from_bottom.xml", "datetime": "1980-00-00 00:00:00", "sha256": "42b9b8856f73003a7bc5a3c7833ce6dec32cdfbd8bbbc02ab2ca5b5df7ec32bb", "type": "XML", "size": 792}, {"detection_ratio": [0, 75], "filename": "res/anim/abc_slide_in_bottom.xml", "datetime": "1980-00-00 00:00:00", "sha256": "342a538d7b0270a2fb31d2c946974aeaa038ddc1729dcd6fdd24496dcb396a50", "type": "XML", "size": 332}, {"detection_ratio": [0, 76], "filename": "res/anim/abc_slide_in_top.xml", "datetime": "1980-00-00 00:00:00", "sha256": "28919aa0d5b59c94fb62a083eb0bfeffbd60ab430ab4bc1b2fccf1c308e68f67", "type": "XML", "size": 332}, {"detection_ratio": [0, 76], "filename": "res/anim/abc_slide_out_bottom.xml", "datetime": "1980-00-00 00:00:00", "sha256": "d685e35dbf4ac79f7741b399b3eb4f38fcacb05dd4905bc01a80bc4b90a2e5a9", "type": "XML", "size": 332}, {"detection_ratio": [0, 74], "filename": "res/anim/abc_slide_out_top.xml", "datetime": "1980-00-00 00:00:00", "sha256": "b6f0da55fc87b5ad19e4b8ebdfe6a2321523480e7a82d0d71e4fd0ce2a102a5a", "type": "XML", "size": 332}, {"size": 332, "sha256": "1e5c2b33af652c115beafe2da3d367e60b067958cbcf7e351f6e8d90966ec963", "type": "XML", "filename": "res/anim/animation_left.xml", "datetime": "1980-00-00 00:00:00"}, {"size": 332, "sha256": "ce77a31f28d5c47b4d1d925f72fecfb66bae5dd1dd9397a54d59b7c083459398", "type": "XML", "filename": "res/anim/animation_left2.xml", "datetime": "1980-00-00 00:00:00"}, {"detection_ratio": [0, 75], "filename": "res/anim/decelerate_cubic.xml", "datetime": "1980-00-00 00:00:00", "sha256": "c5ca0c3d977b5b1d60322a29114e8fb85765a62ccfe1233f92f9f440f3eb7f6f", "type": "XML", "size": 220}, {"detection_ratio": [0, 73], "filename": "res/anim/design_fab_in.xml", "datetime": "1980-00-00 00:00:00", "sha256": "c00ffa19a1f57c16beaecece1efbedcc15ae203366a9da2a0086b7eed1643395", "type": "XML", "size": 620}, {"detection_ratio": [0, 73], "filename": "res/anim/design_fab_out.xml", "datetime": "1980-00-00 00:00:00", "sha256": "ee443b3f78279bb2f03a1bbe8ef06c86b925cd6d598621b8d92eeb811f15bade", "type": "XML", "size": 620}, {"detection_ratio": [0, 73], "filename": "res/anim/design_snackbar_in.xml", "datetime": "1980-00-00 00:00:00", "sha256": "e6bc965c64d7a1288b565124618c99a44340c4680a89f1b59177a5be2072ac7f", "type": "XML", "size": 252}, {"detection_ratio": [0, 73], "filename": "res/anim/design_snackbar_out.xml", "datetime": "1980-00-00 00:00:00", "sha256": "f39190eca88cd67041a1cb074f0e79d7d60d5955173f8ad4ab6ecc2cc150c9d1", "type": "XML", "size": 252}, {"detection_ratio": [0, 74], "filename": "res/anim/popup_enter.xml", "datetime": "1980-00-00 00:00:00", "sha256": "d7080e8e01e2b8775fd2202f17274c1329d37c97518795dd3cd0808ef05d7ab6", "type": "XML", "size": 444}, {"detection_ratio": [0, 74], "filename": "res/anim/popup_exit.xml", "datetime": "1980-00-00 00:00:00", "sha256": "d250621c635be80b969fe84f27606a9117bdffc9866eb6e57d3114b0e0294c7d", "type": "XML", "size": 444}, {"size": 788, "sha256": "365894d953b476b5a1a6c968e0b40867c033616e5043b9b4124ba704f41f6b9c", "type": "XML", "filename": "res/anim/raise.xml", "datetime": "1980-00-00 00:00:00"}, {"detection_ratio": [0, 69], "filename": "res/color-v11/abc_background_cache_hint_selector_material_dark.xml", "datetime": "1980-00-00 00:00:00", "sha256": "7005de5844a2321c57c91edc3041892079ded87fabb81b122434b22b97eb4b47", "type": "XML", "size": 404}, {"detection_ratio": [0, 73], "filename": "res/color-v11/abc_background_cache_hint_selector_material_light.xml", "datetime": "1980-00-00 00:00:00", "sha256": "47df89f97af9149a711361f42f2bb996ac21a75142b349a7261ecad29b2e995d", "type": "XML", "size": 404}, {"detection_ratio": [0, 73], "filename": "res/color-v23/abc_color_highlight_material.xml", "datetime": "1980-00-00 00:00:00", "sha256": "de0ba01c59d6255536d60d7f937d2a65d684966172299afcda9e1087522cda81", "type": "XML", "size": 480}, {"detection_ratio": [0, 69], "filename": "res/color/abc_primary_text_disable_only_material_dark.xml", "datetime": "1980-00-00 00:00:00", "sha256": "b00845b3b9db81a4280406733e43c73dbcebccab4efc933d09184927a6356ffb", "type": "XML", "size": 400}, {"detection_ratio": [0, 70], "filename": "res/color/abc_primary_text_disable_only_material_light.xml", "datetime": "1980-00-00 00:00:00", "sha256": "2d3b1b49ccddf6bb416635e687e89f6edbfc4e6299b67f9b97bc11ab4a174cf9", "type": "XML", "size": 400}, {"size": 400, "sha256": "fa8152825d72900fae7fc3546c4c1227fcbc970be7940f0565d6c6df1b5929f1", "type": "XML", "filename": "res/color/abc_primary_text_material_dark.xml", "datetime": "1980-00-00 00:00:00"}, {"size": 400, "sha256": "5f282833ed6ff3ee17ff66db0d61dbb1b8c354fafc4248475b862c6d5da1868b", "type": "XML", "filename": "res/color/abc_primary_text_material_light.xml", "datetime": "1980-00-00 00:00:00"}, {"detection_ratio": [0, 69], "filename": "res/color/abc_search_url_text.xml", "datetime": "1980-00-00 00:00:00", "sha256": "c8a6825bf21820af399307eaccaa293ee00a65e607418312ac7b7a1bbd0c0130", "type": "XML", "size": 524}, {"size": 400, "sha256": "cf61b52b2124081ecb24e464a737d00710284e877d10b0d783676df984586480", "type": "XML", "filename": "res/color/abc_secondary_text_material_dark.xml", "datetime": "1980-00-00 00:00:00"}, {"detection_ratio": [0, 75], "filename": "res/color/abc_secondary_text_material_light.xml", "datetime": "1980-00-00 00:00:00", "sha256": "456124f45698901b87ad8629cb3d2e3b79d102f27e048141861606f357628d50", "type": "XML", "size": 400}, {"size": 648, "sha256": "f566286fcee6d2541b7e7209ac7b489b9f767a520e110724931a06a18a058f65", "type": "XML", "filename": "res/color/common_google_signin_btn_text_dark.xml", "datetime": "1980-00-00 00:00:00"}, {"detection_ratio": [0, 74], "filename": "res/color/common_google_signin_btn_text_light.xml", "datetime": "1980-00-00 00:00:00", "sha256": "84d272a9ca80851e28e3cd5cc67ac698d3479d7a3ac32997386bfae46ac3c156", "type": "XML", "size": 648}, {"detection_ratio": [0, 73], "filename": "res/color/common_google_signin_btn_tint.xml", "datetime": "1980-00-00 00:00:00", "sha256": "3dd7b82854396b6a07c27bb20bd8f71c00ff95dc57342db3364dbe8fa40eaec1", "type": "XML", "size": 400}], "uncompressed_size": 20170168}, "first_seen_itw": "2020-04-25 06:25:13", "androguard": {"Activities": ["ir.teb_eslami_orkideh.material.Splash", "ir.teb_eslami_orkideh.material.MainActivity", "ir.teb_eslami_orkideh.material.DetailActivity", "ir.teb_eslami_orkideh.Push", "ir.teb_eslami_orkideh.Pushtelegram", "ir.teb_eslami_orkideh.PopUpPush", "ir.teb_eslami_orkideh.PopDialog", "ir.teb_eslami_orkideh.Dialog", "ir.teb_eslami_orkideh.imgshow", "ir.teb_eslami_orkideh.imgshowtop", "ir.adad.client.AdadActivity", "co.ronash.pushe.activities.PopupDialogActivity", "co.ronash.pushe.activities.WebviewActivity", "co.ronash.pushe.activities.RequestAccessDialogActivity", "com.google.android.gms.common.api.GoogleApiActivity", "com.onesignal.PermissionsActivity"], "AndroidVersionCode": "6", "certificate": {"Subject": {"DN": "OU:Navid System, CN:Orkideh Team, O:Navid System", "OU": "Navid System", "CN": "Orkideh Team", "O": "Navid System"}, "validto": "2116-07-17 22:19:11", "serialnumber": "623d7ee6", "thumbprint": "304ebe2119e45567867b7624bf10a026755dffa1", "validfrom": "2017-08-10 22:19:11", "Issuer": {"DN": "OU:Navid System, CN:Orkideh Team, O:Navid System", "OU": "Navid System", "CN": "Orkideh Team", "O": "Navid System"}}, "VTAndroidInfo": 1.41, "AndroidApplication": 1, "Package": "ir.teb_eslami_orkideh", "StringsInformation": ["http://", "http://schemas.android.com/apk/res/android", "http://xmlpull.org/v1/doc/features.html#indent-output", "https://", "https://app-measurement.com/a", "https://instagram.com/_u/", "https://js.adad.ir/adad-client/js/", "https://onesignal.com/android_frame.html", "https://onesignal.com/api/v1/", "https://pagead2.googlesyndication.com/pagead/gen_204?id=gmob-apps", "https://plus.google.com/", "https://www.google.com", "https://www.googleapis.com/auth/appstate", "https://www.googleapis.com/auth/datastoremobile", "https://www.googleapis.com/auth/drive.appdata", "https://www.googleapis.com/auth/drive.file", "https://www.googleapis.com/auth/fitness.activity.read", "https://www.googleapis.com/auth/fitness.activity.write", "https://www.googleapis.com/auth/fitness.body.read", "https://www.googleapis.com/auth/fitness.body.write", "https://www.googleapis.com/auth/fitness.location.read", "https://www.googleapis.com/auth/fitness.location.write", "https://www.googleapis.com/auth/fitness.nutrition.read", "https://www.googleapis.com/auth/fitness.nutrition.write", "https://www.googleapis.com/auth/games", "https://www.googleapis.com/auth/games_lite", "https://www.googleapis.com/auth/plus.login", "https://www.googleapis.com/auth/plus.me"], "intent-filters": {"Services": {"co.ronash.pushe.service.InstanceIDService": {"action": ["com.google.android.gms.iid.InstanceID"]}, "co.ronash.pushe.service.GcmService": {"action": ["com.google.android.c2dm.intent.RECEIVE"]}, "ir.teb_eslami_orkideh.MyPushListener": {"action": ["co.ronash.pushe.RECEIVE"]}, "com.evernote.android.job.gcm.PlatformGcmService": {"action": ["com.google.android.gms.gcm.ACTION_TASK_READY"]}, "co.ronash.pushe.service.FallbackGcmTaskRunner": {"action": ["co.ronash.pushe.ACTION_TASK_READY"]}, "co.ronash.pushe.task.scheduler.gcm.GcmTaskRunner": {"action": ["com.google.android.gms.gcm.ACTION_TASK_READY"]}, "co.ronash.pushe.service.ScreenStateService": {"action": ["co.ronash.pushe.service.ScreenStateService"]}, "com.google.firebase.iid.FirebaseInstanceIdService": {"action": ["com.google.firebase.INSTANCE_ID_EVENT"]}, "ir.teb_eslami_orkideh.onejson": {"action": ["com.onesignal.NotificationExtender"]}}, "Activities": {"ir.teb_eslami_orkideh.material.Splash": {"action": ["android.intent.action.MAIN"], "category": ["android.intent.category.DEFAULT", "android.intent.category.LAUNCHER"]}}, "Receivers": {"co.ronash.pushe.receiver.BootAndScreenReceiver": {"action": ["android.intent.action.BOOT_COMPLETED", "android.intent.action.QUICKBOOT_POWERON"]}, "co.ronash.pushe.receiver.AppChangeReceiver": {"action": ["android.intent.action.PACKAGE_INSTALL", "android.intent.action.PACKAGE_ADDED", "android.intent.action.PACKAGE_FULLY_REMOVED"]}, "com.onesignal.BootUpReceiver": {"action": ["android.intent.action.ACTION_BOOT_COMPLETED", "android.intent.action.BOOT_COMPLETED", "android.intent.action.QUICKBOOT_POWERON"]}, "com.evernote.android.job.v14.PlatformAlarmReceiver": {"action": ["com.evernote.android.job.v14.RUN_JOB", "net.vrallev.android.job.v14.RUN_JOB"]}, "com.google.android.gms.gcm.GcmReceiver": {"action": ["com.google.android.c2dm.intent.RECEIVE", "com.google.android.c2dm.intent.REGISTRATION"], "category": ["ir.teb_eslami_orkideh"]}, "com.evernote.android.job.JobBootReceiver": {"action": ["android.intent.action.BOOT_COMPLETED", "android.intent.action.QUICKBOOT_POWERON", "com.htc.intent.action.QUICKBOOT_POWERON", "android.intent.action.MY_PACKAGE_REPLACED"]}, "com.onesignal.UpgradeReceiver": {"action": ["android.intent.action.MY_PACKAGE_REPLACED"]}, "co.ronash.pushe.receiver.UpdateReceiver": {"action": ["android.intent.action.PACKAGE_REPLACED"]}, "com.google.android.gms.measurement.AppMeasurementInstallReferrerReceiver": {"action": ["com.android.vending.INSTALL_REFERRER"]}, "com.google.firebase.iid.FirebaseInstanceIdReceiver": {"action": ["com.google.android.c2dm.intent.RECEIVE"], "category": ["ir.teb_eslami_orkideh"]}, "co.ronash.pushe.receiver.ConnectivityReceiver": {"action": ["android.net.conn.CONNECTIVITY_CHANGE"]}, "co.ronash.pushe.receiver.FallbackGcmNetworkManagerReceiver": {"action": ["co.ronash.pushe.CHECK_TASKS"]}, "co.ronash.pushe.receiver.AddReceiver": {"action": ["com.evernote.android.job.ADD_JOB_CREATOR"]}, "com.onesignal.GcmBroadcastReceiver": {"action": ["com.google.android.c2dm.intent.RECEIVE"], "category": ["ir.teb_eslami_orkideh"]}}}, "Main Activity": "ir.teb_eslami_orkideh.material.Splash", "Libraries": [], "AndroidApplicationError": false, "Providers": ["co.ronash.pushe.provider.PusheProvider", "com.google.firebase.provider.FirebaseInitProvider"], "AndroidVersionName": "1.0", "RiskIndicator": {"APK": {"DEX": 1}, "PERM": {"INTERNET": 1, "PRIVACY": 1, "NORMAL": 7, "SIGNATURE": 1}}, "Services": ["ir.teb_eslami_orkideh.MyPushListener", "ir.teb_eslami_orkideh.onejson", "co.ronash.pushe.service.GcmService", "co.ronash.pushe.service.ScreenStateService", "co.ronash.pushe.service.FallbackGcmTaskRunner", "co.ronash.pushe.task.scheduler.gcm.GcmTaskRunner", "co.ronash.pushe.service.IntentTaskRunner", "co.ronash.pushe.service.InstanceIDService", "co.ronash.pushe.service.PusheActivityService", "com.evernote.android.job.gcm.PlatformGcmService", "co.ronash.pushe.task.tasks.NetworkConnect", "co.ronash.pushe.receiver.PusheGcmReceiver", "com.google.android.gms.measurement.AppMeasurementService", "com.google.android.gms.measurement.AppMeasurementJobService", "com.google.firebase.iid.FirebaseInstanceIdService", "com.onesignal.GcmIntentService", "com.onesignal.GcmIntentJobService", "com.onesignal.RestoreJobService", "com.onesignal.RestoreKickoffJobService", "com.onesignal.SyncService", "com.onesignal.SyncJobService", "com.onesignal.NotificationRestoreService", "com.evernote.android.job.v21.PlatformJobService", "com.evernote.android.job.v14.PlatformAlarmService", "com.evernote.android.job.v14.PlatformAlarmServiceExact", "com.evernote.android.job.JobRescheduleService"], "MinSdkVersion": "16", "AndroidApplicationInfo": "APK", "TargetSdkVersion": "23", "Receivers": ["co.ronash.pushe.receiver.UpdateReceiver", "com.google.android.gms.gcm.GcmReceiver", "co.ronash.pushe.receiver.FallbackGcmNetworkManagerReceiver", "co.ronash.pushe.receiver.BootAndScreenReceiver", "co.ronash.pushe.receiver.ConnectivityReceiver", "co.ronash.pushe.receiver.AddReceiver", "co.ronash.pushe.receiver.AppChangeReceiver", "com.google.android.gms.measurement.AppMeasurementReceiver", "com.google.android.gms.measurement.AppMeasurementInstallReferrerReceiver", "com.google.firebase.iid.FirebaseInstanceIdReceiver", "com.onesignal.GcmBroadcastReceiver", "com.onesignal.NotificationOpenedReceiver", "com.onesignal.BootUpReceiver", "com.onesignal.UpgradeReceiver", "com.evernote.android.job.v14.PlatformAlarmReceiver", "com.evernote.android.job.JobBootReceiver"], "AndroguardVersion": "3.0-dev", "Permissions": {"com.huawei.android.launcher.permission.WRITE_SETTINGS": ["normal", "modify global system settings", "Allows an application to modify the system's settings data. Malicious applications can corrupt your system's configuration."], "com.huawei.android.launcher.permission.CHANGE_BADGE": ["normal", "Unknown permission from android reference", "Unknown permission from android reference"], "android.permission.INTERNET": ["dangerous", "full Internet access", "Allows an application to create network sockets."], "com.sec.android.provider.badge.permission.WRITE": ["normal", "Unknown permission from android reference", "Unknown permission from android reference"], "com.oppo.launcher.permission.READ_SETTINGS": ["normal", "Unknown permission from android reference", "Unknown permission from android reference"], "com.majeur.launcher.permission.UPDATE_BADGE": ["normal", "Unknown permission from android reference", "Unknown permission from android reference"], "com.google.android.c2dm.permission.RECEIVE": ["normal", "Unknown permission from android reference", "Unknown permission from android reference"], "android.permission.ACCESS_NETWORK_STATE": ["normal", "view network status", "Allows an application to view the status of all networks."], "me.everything.badger.permission.BADGE_COUNT_READ": ["normal", "Unknown permission from android reference", "Unknown permission from android reference"], "com.htc.launcher.permission.UPDATE_SHORTCUT": ["normal", "Unknown permission from android reference", "Unknown permission from android reference"], "android.permission.BIND_JOB_SERVICE": ["normal", "Unknown permission from android reference", "Unknown permission from android reference"], "me.everything.badger.permission.BADGE_COUNT_WRITE": ["normal", "Unknown permission from android reference", "Unknown permission from android reference"], "android.permission.RECEIVE_BOOT_COMPLETED": ["normal", "automatically start at boot", "Allows an application to start itself as soon as the system has finished booting. This can make it take longer to start the phone and allow the application to slow down the overall phone by always running."], "com.anddoes.launcher.permission.UPDATE_COUNT": ["normal", "Unknown permission from android reference", "Unknown permission from android reference"], "com.sonymobile.home.permission.PROVIDER_INSERT_BADGE": ["normal", "Unknown permission from android reference", "Unknown permission from android reference"], "android.permission.READ_PHONE_STATE": ["dangerous", "read phone state and identity", "Allows the application to access the phone features of the device. An application with this permission can determine the phone number and serial number of this phone, whether a call is active, the number that call is connected to and so on."], "com.oppo.launcher.permission.WRITE_SETTINGS": ["normal", "modify global system settings", "Allows an application to modify the system's settings data. Malicious applications can corrupt your system's configuration."], "android.permission.VIBRATE": ["normal", "control vibrator", "Allows the application to control the vibrator."], "com.google.android.gms.permission.ACTIVITY_RECOGNITION": ["normal", "Unknown permission from android reference", "Unknown permission from android reference"], "com.sonyericsson.home.permission.BROADCAST_BADGE": ["normal", "Unknown permission from android reference", "Unknown permission from android reference"], "com.huawei.android.launcher.permission.READ_SETTINGS": ["normal", "Unknown permission from android reference", "Unknown permission from android reference"], "android.permission.ACCESS_WIFI_STATE": ["normal", "view Wi-Fi status", "Allows an application to view the information about the status of Wi-Fi."], "android.permission.WAKE_LOCK": ["normal", "prevent phone from sleeping", "Allows an application to prevent the phone from going to sleep."], "ir.teb_eslami_orkideh.permission.C2D_MESSAGE": ["signature", "C2DM permission.", "C2DM permission."], "com.htc.launcher.permission.READ_SETTINGS": ["normal", "Unknown permission from android reference", "Unknown permission from android reference"], "com.sec.android.provider.badge.permission.READ": ["normal", "Unknown permission from android reference", "Unknown permission from android reference"], "android.permission.READ_APP_BADGE": ["normal", "Unknown permission from android reference", "Unknown permission from android reference"]}}}, "size": 5101776, "scan_id": "8b932c0b788b1652e639a6e1427d4efceb54655137bbc6e69df81be19a813a04-1618461280", "total": 61, "harmless_votes": 0, "verbose_msg": "Scan finished, information embedded", "sha256": "8b932c0b788b1652e639a6e1427d4efceb54655137bbc6e69df81be19a813a04", "type": "Android", "scans": {"Bkav": {"detected": false, "version": "1.3.0.9899", "result": null, "update": "20210414"}, "MicroWorld-eScan": {"detected": false, "version": "14.0.409.0", "result": null, "update": "20210415"}, "FireEye": {"detected": false, "version": "32.44.1.0", "result": null, "update": "20210415"}, "CAT-QuickHeal": {"detected": true, "version": "14.00", "result": "Android.Notifyer.A1f42 (AdWare)", "update": "20210414"}, "McAfee": {"detected": true, "version": "6.0.6.653", "result": "Artemis!0364F1A3FDDD", "update": "20210415"}, "Malwarebytes": {"detected": false, "version": "4.2.1.18", "result": null, "update": "20210413"}, "VIPRE": {"detected": false, "version": "91838", "result": null, "update": "20210415"}, "SUPERAntiSpyware": {"detected": false, "version": "5.6.0.1032", "result": null, "update": "20210409"}, "K7AntiVirus": {"detected": false, "version": "11.176.36933", "result": null, "update": "20210415"}, "Alibaba": {"detected": true, "version": "0.3.0.5", "result": "AdWare:Android/Notifyer.95445f78", "update": "20190527"}, "K7GW": {"detected": true, "version": "11.176.36921", "result": "Trojan ( 005514031 )", "update": "20210414"}, "Trustlook": {"detected": false, "version": "1.0", "result": null, "update": "20210415"}, "Arcabit": {"detected": false, "version": "1.0.0.881", "result": null, "update": "20210415"}, "Baidu": {"detected": false, "version": "1.0.0.2", "result": null, "update": "20190318"}, "Cyren": {"detected": true, "version": "6.3.0.2", "result": "Trojan.OLRP-9", "update": "20210415"}, "SymantecMobileInsight": {"detected": true, "version": "2.0", "result": "AppRisk:Generisk", "update": "20210126"}, "Symantec": {"detected": true, "version": "1.14.0.0", "result": "Trojan.Gen.MBT", "update": "20210414"}, "ESET-NOD32": {"detected": true, "version": "23134", "result": "a variant of Android/AdDisplay.AdPush.A potentially unwanted", "update": "20210415"}, "TrendMicro-HouseCall": {"detected": false, "version": "10.0.0.1040", "result": null, "update": "20210415"}, "Avast": {"detected": false, "version": "21.1.5827.0", "result": null, "update": "20210415"}, "ClamAV": {"detected": false, "version": "0.103.2.0", "result": null, "update": "20210414"}, "Kaspersky": {"detected": true, "version": "21.0.1.45", "result": "not-a-virus:HEUR:AdWare.AndroidOS.Notifyer.an", "update": "20210415"}, "BitDefender": {"detected": false, "version": "7.2", "result": null, "update": "20210415"}, "NANO-Antivirus": {"detected": true, "version": "1.0.146.25279", "result": "Riskware.Android.Notifyer.gbzipn", "update": "20210415"}, "AegisLab": {"detected": true, "version": "4.2", "result": "Adware.AndroidOS.Notifyer.A!c", "update": "20210415"}, "Tencent": {"detected": false, "version": "1.0.0.1", "result": null, "update": "20210415"}, "Ad-Aware": {"detected": false, "version": "3.0.16.117", "result": null, "update": "20210415"}, "Emsisoft": {"detected": false, "version": "2018.12.0.1641", "result": null, "update": "20210415"}, "Comodo": {"detected": false, "version": "33439", "result": null, "update": "20210414"}, "F-Secure": {"detected": false, "version": "12.0.86.52", "result": null, "update": "20210331"}, "DrWeb": {"detected": true, "version": "7.0.49.9080", "result": "Adware.Adpush.1143", "update": "20210415"}, "Zillya": {"detected": true, "version": "2.0.0.4341", "result": "Adware.Notifyer.Android.32", "update": "20210414"}, "McAfee-GW-Edition": {"detected": true, "version": "v2019.1.2+3728", "result": "Artemis", "update": "20210414"}, "CMC": {"detected": false, "version": "2.10.2019.1", "result": null, "update": "20210327"}, "Sophos": {"detected": false, "version": "1.0.2.0", "result": null, "update": "20210414"}, "Avast-Mobile": {"detected": false, "version": "210414-10", "result": null, "update": "20210414"}, "Jiangmin": {"detected": false, "version": "16.0.100", "result": null, "update": "20210414"}, "Avira": {"detected": true, "version": "8.3.3.12", "result": "ANDROID/Hiddad.FCD.Gen", "update": "20210415"}, "MAX": {"detected": false, "version": "2019.9.16.1", "result": null, "update": "20210415"}, "Antiy-AVL": {"detected": false, "version": "3.0.0.1", "result": null, "update": "20210412"}, "Kingsoft": {"detected": false, "version": "2017.9.26.565", "result": null, "update": "20210415"}, "Gridinsoft": {"detected": false, "version": "1.0.37.128", "result": null, "update": "20210415"}, "Microsoft": {"detected": true, "version": "1.1.18000.5", "result": "PUA:Win32/Bitrepeyp.B", "update": "20210415"}, "ViRobot": {"detected": false, "version": "2014.3.20.0", "result": null, "update": "20210415"}, "ZoneAlarm": {"detected": false, "version": "1.0", "result": null, "update": "20210415"}, "GData": {"detected": false, "version": "A:25.29323B:27.22661", "result": null, "update": "20210415"}, "Cynet": {"detected": true, "version": "4.0.0.27", "result": "Malicious (score: 99)", "update": "20210412"}, "BitDefenderFalx": {"detected": true, "version": "2.0.936", "result": "Android.Riskware.Agent.gHJXI", "update": "20200916"}, "AhnLab-V3": {"detected": true, "version": "3.19.7.10132", "result": "PUP/Android.FLPrev.999519", "update": "20210415"}, "BitDefenderTheta": {"detected": false, "version": "7.2.37796.0", "result": null, "update": "20210414"}, "ALYac": {"detected": false, "version": "1.1.3.1", "result": null, "update": "20210415"}, "TACHYON": {"detected": false, "version": "2021-04-15.01", "result": null, "update": "20210415"}, "VBA32": {"detected": false, "version": "5.0.0", "result": null, "update": "20210414"}, "Zoner": {"detected": false, "version": "0.0.0.0", "result": null, "update": "20210414"}, "Rising": {"detected": false, "version": "25.0.0.26", "result": null, "update": "20210414"}, "Yandex": {"detected": false, "version": "5.5.2.24", "result": null, "update": "20210413"}, "Ikarus": {"detected": true, "version": "0.1.5.2", "result": "PUA.AndroidOS.Hiddad", "update": "20210414"}, "MaxSecure": {"detected": false, "version": "1.0.0.1", "result": null, "update": "20210414"}, "Fortinet": {"detected": true, "version": "6.2.142.0", "result": "Adware/Notifyer!Android", "update": "20210414"}, "Panda": {"detected": false, "version": "4.6.4.2", "result": null, "update": "20210414"}, "Qihoo-360": {"detected": true, "version": "1.0.0.1120", "result": "Android/Adware.Generic.HgMASOQA", "update": "20210415"}}, "tags": ["telephony", "android", "via-tor", "reflection", "apk"], "authentihash": null, "unique_sources": 2, "positives": 22, "ssdeep": "98304:RwxYVvZES2wERTdjQxyQfBZpSH7snhRbrzoWuXHiUVuvB4CU4:RKYVvCS2dRTdjc5ZpSQhRboYJ4u", "md5": "0364f1a3fddde8ceb096817fb59888dd", "permalink": "https://www.virustotal.com/gui/file/8b932c0b788b1652e639a6e1427d4efceb54655137bbc6e69df81be19a813a04/detection/f-8b932c0b788b1652e639a6e1427d4efceb54655137bbc6e69df81be19a813a04-1618461280", "sha1": "1e0b412576eeb879aba0887a9022f797ea8d7815", "submission": {"submitter_region": "bw", "submitter_country": "DE", "date": "2021-04-15 04:34:40", "filename": "0364f1a3fddde8ceb096817fb59888dd.apk"}, "response_code": 1, "community_reputation": 0, "malicious_votes": 0, "ITW_urls": ["https://cafe.bzrcdn.net/1/UEPgKhiwwagD2YsiNQmd_A/1570511485/apks/243721649740.apk"], "last_seen": "2021-04-15 04:34:40"}