{"vhash": "4825ee886a1f03919c9e4fe301a84eb9", "submission_names": ["/var/www/clean-mx/virusesevidence/output.156931024.txt", "Mario.ZXC.apk", "cjmla.apk", "mario.zxc.apk", "/var/www/clean-mx/virusesevidence/output.146023550.txt"], "scan_date": "2021-04-15 03:23:51", "first_seen": "2017-03-10 07:20:27", "times_submitted": 7, "additional_info": {"email_parents": [], "magic": "Zip archive data, at least v2.0 to extract", "sigcheck": {}, "exiftool": {"ZipRequiredVersion": "20", "MIMEType": "application/zip", "ZipCRC": "0xf9598322", "FileType": "ZIP", "ZipCompression": "Deflated", "ZipUncompressedSize": "7504", "ZipCompressedSize": "1784", "FileTypeExtension": "zip", "ZipFileName": "AndroidManifest.xml", "ZipBitFlag": "0x0808", "ZipModifyDate": "2014:01:02 08:44:00"}, "trid": "Android Package (46.6%)\nJava Enterprise Archive (23.6%)\nJava Archive (16.3%)\nUniversal Scene Description Zipped AR format (generic) (7.2%)\nZIP compressed archive (4.8%)", "positives_delta": 3, "compressedview": {"highest_datetime": "2016-06-02 08:43:48", "tags": [], "lowest_datetime": "2010-10-12 11:13:16", "num_children": 372, "extensions": {"xml": 14, "dex": 1, "MF": 1, "jar": 1, "RSA": 1, "jpg": 31, "SF": 1, "dat": 227, "mp3": 48, "ttf": 1, "png": 45}, "file_types": {"XML": 14, "DEX": 1, "ZIP": 1, "unknown": 263, "JPG": 31, "RAR": 1, "MP3": 16, "PNG": 45}, "type": "APK", "children": [{"size": 7504, "sha256": "e389f8733d517bcd93a46c1590026b912934d8fb897e2d4afccd4d23f131f62d", "type": "XML", "filename": "AndroidManifest.xml", "datetime": "2014-01-02 08:44:00"}, {"size": 58861, "sha256": "222073919a7bc4b26b8bf0bd9a8a5236309b89d0a671cc000d188cc97c1c2bcb", "type": "PNG", "filename": "assets/bg/bg1.png", "datetime": "2014-01-28 09:43:44"}, {"detection_ratio": [0, 56], "filename": "assets/bg/bg10.png", "datetime": "2014-04-21 11:31:52", "sha256": "e4e3219920ea97aa5fa40de5f5a2c67273cb1d07658bb0fcbd97db63935dc218", "type": "PNG", "size": 156}, {"size": 8659, "sha256": "ef6d3db5375aaa860cf3459351cebf8a60ac879a852eba6ce1c8b076bc41cde4", "type": "PNG", "filename": "assets/bg/bg11.png", "datetime": "2014-02-18 11:55:26"}, {"size": 17333, "sha256": "0b09f54bf9642c784e0de3970e17309ed6c4dd8bec1a8de99e933365d25c20cb", "type": "PNG", "filename": "assets/bg/bg12.png", "datetime": "2014-02-17 17:27:28"}, {"detection_ratio": [0, 56], "filename": "assets/bg/bg13.png", "datetime": "2014-02-26 16:24:58", "sha256": "b587c7bc8f0a9b8c251154129ec16ab7c0967e8eae8eda8e2308edc6e86c0717", "type": "PNG", "size": 47286}, {"detection_ratio": [0, 56], "filename": "assets/bg/bg14.png", "datetime": "2014-02-26 14:13:06", "sha256": "0af0726e0f7e556d58b6405ceb9eaf3c5658e666a7c12f6cd052b59da8a9a487", "type": "PNG", "size": 77692}, {"detection_ratio": [0, 56], "filename": "assets/bg/bg15.png", "datetime": "2014-02-26 14:14:48", "sha256": "bab140fd38c5224f803408d225e86c65cf6fc222fef8c1da63091c0690844a81", "type": "PNG", "size": 99251}, {"size": 151375, "sha256": "758356a8755785ab1ebb1f2a34df599a0fcd9e6d0cc49e42a72736cb7d2bfdd8", "type": "PNG", "filename": "assets/bg/bg16.png", "datetime": "2014-06-05 08:53:34"}, {"detection_ratio": [0, 56], "filename": "assets/bg/bg17.png", "datetime": "2014-03-11 16:09:52", "sha256": "f08dc71a47e7aa6ff5ef842fdb7ddbe02c5482a097446f76551bc16d0be07e76", "type": "PNG", "size": 306129}, {"detection_ratio": [0, 56], "filename": "assets/bg/bg18.png", "datetime": "2014-03-30 14:49:42", "sha256": "44d148b69fc5902b4f9656923c757a4083e25e555a9e89bcb01df2bd70d72cab", "type": "PNG", "size": 5820}, {"detection_ratio": [0, 56], "filename": "assets/bg/bg19.png", "datetime": "2014-06-03 14:06:52", "sha256": "2dcc541e81c7ab8b2b5b75b1755b3ff0ef9c5ba93f9c92af96094de29e94b1ab", "type": "PNG", "size": 155126}, {"size": 101191, "sha256": "226fc87aaf2182d8ef092983b57aeef609b7c2edbed13c331d83816326ab15c6", "type": "PNG", "filename": "assets/bg/bg2.png", "datetime": "2014-01-28 10:54:56"}, {"detection_ratio": [0, 55], "filename": "assets/bg/bg20.png", "datetime": "2014-04-19 17:59:12", "sha256": "756e7a1795d10128c29e685987fbcff7badc9ed73f2c919641d0f0fe73a89d8d", "type": "PNG", "size": 10979}, {"detection_ratio": [0, 55], "filename": "assets/bg/bg21.png", "datetime": "2014-04-21 15:41:32", "sha256": "8107e9eb53aa13ae78a8856d6cc472c721fe8a9c8e614346aa5949b7e815cf70", "type": "PNG", "size": 2304}, {"detection_ratio": [0, 56], "filename": "assets/bg/bg22.png", "datetime": "2014-04-21 09:24:14", "sha256": "21ea8b6645f5f8f45a5b22b7fff775af3388961ae203c03bb4a0bcd3c65a0a1a", "type": "PNG", "size": 157552}, {"detection_ratio": [0, 56], "filename": "assets/bg/bg23.png", "datetime": "2014-05-08 16:32:06", "sha256": "a0ae0fdf4f94f808cb987dd43cdde5a95a5946504c5e36259614fd767e3c3244", "type": "PNG", "size": 6191}, {"detection_ratio": [0, 56], "filename": "assets/bg/bg24.png", "datetime": "2014-07-27 11:27:32", "sha256": "0de4a9adb626b327dcd29fbd48a252f98c8ae07673bc8bd96d445aad2dfa8233", "type": "PNG", "size": 188319}, {"size": 36708, "sha256": "a1b2e927d4bb9ec90b7b6f169be685f9f7ef29ded5b44f4783da4b83d7513143", "type": "PNG", "filename": "assets/bg/bg3.png", "datetime": "2014-01-28 11:11:20"}, {"size": 7620, "sha256": "0bc21d8d8dd4bbf67fcc450dde05a8471079b509b94cbb1d703e9d9c1a3f6e49", "type": "PNG", "filename": "assets/bg/bg4.png", "datetime": "2014-01-28 11:15:32"}, {"size": 4502, "sha256": "7662f863d14ec56e66fd331fb68f88add431c25bbbe184b35d8f127b728b4742", "type": "PNG", "filename": "assets/bg/bg5.png", "datetime": "2014-01-28 11:32:02"}, {"size": 10151, "sha256": "3eacb59509c818fd3b0c454cfee3d533947af8070a732bdbe17d114dcea5fe4b", "type": "PNG", "filename": "assets/bg/bg6.png", "datetime": "2014-01-28 15:10:54"}, {"size": 15133, "sha256": "d3bd459d12f3621a19bd172a39d34242540415426cf6e8c01b965700c96d741f", "type": "PNG", "filename": "assets/bg/bg7.png", "datetime": "2014-01-28 11:38:08"}, {"size": 29917, "sha256": "f1b0094c76a9871e87726728e0e43a359e4a3ac4471d0425ecb1e6cb0380531f", "type": "PNG", "filename": "assets/bg/bg8.png", "datetime": "2014-01-28 14:23:14"}, {"size": 8459, "sha256": "dc8c6eb1bfd553d23fcf56cea49e93d44a485ab3b20c8c3d9d2a37a4607a33b3", "type": "PNG", "filename": "assets/bg/bg9.png", "datetime": "2014-01-28 14:51:28"}, {"detection_ratio": [0, 56], "filename": "assets/blast/blast1.dat", "datetime": "2014-03-13 08:28:46", "sha256": "6d50c339e344694fc29b9b1bcd30dd52d1f0510fa4cf6a53e327a67c8f01b1d8", "type": "unknown", "size": 603}, {"detection_ratio": [0, 56], "filename": "assets/blast/blast10.dat", "datetime": "2014-03-13 08:28:46", "sha256": "2d69dcdbdc65173d0d5f0422889868976d7be704fc6a0c9e1cbf631f21372ff3", "type": "unknown", "size": 3573}, {"detection_ratio": [0, 56], "filename": "assets/blast/blast11.dat", "datetime": "2014-03-13 08:28:46", "sha256": "560e9a795b1f10c74bc192d50562db2eee044c3a29a78540279104ce75ca9612", "type": "unknown", "size": 4734}, {"detection_ratio": [0, 56], "filename": "assets/blast/blast12.dat", "datetime": "2014-03-13 08:28:46", "sha256": "8a337e75af4e177f33ad1ebeb7a991172fba551e7a94dc897e6a8220ce0ad36d", "type": "unknown", "size": 4257}, {"detection_ratio": [0, 56], "filename": "assets/blast/blast13.dat", "datetime": "2014-03-13 08:28:46", "sha256": "de39fc3a4dca085a2003dbcdec5b05c83b97d455dff9119c3aa1dd16eb6b83da", "type": "unknown", "size": 3681}, {"detection_ratio": [0, 56], "filename": "assets/blast/blast14.dat", "datetime": "2014-01-02 08:44:00", "sha256": "bcf5436bfccc8256634ca1c59b869ed3ff78f64b855c1e8f4d3bf794776935ac", "type": "unknown", "size": 4320}, {"detection_ratio": [0, 56], "filename": "assets/blast/blast15.dat", "datetime": "2014-01-02 08:44:00", "sha256": "5bdfd9832d585072e467a02a64bf2a75781a80316b78310e8711ee28ff397199", "type": "unknown", "size": 3762}, {"detection_ratio": [0, 56], "filename": "assets/blast/blast16.dat", "datetime": "2014-03-13 08:28:46", "sha256": "75d4e4271b6fce53084a7634b21e16fecf486d598e9f232a13eac10134df4647", "type": "unknown", "size": 3330}, {"detection_ratio": [0, 56], "filename": "assets/blast/blast17.dat", "datetime": "2014-03-13 08:28:46", "sha256": "c64bb738dae7d19f5722ae945a3531fd21fe434e47f5ee7bdc13297cf46feb39", "type": "unknown", "size": 4446}, {"detection_ratio": [0, 56], "filename": "assets/blast/blast18.dat", "datetime": "2014-03-13 08:28:46", "sha256": "46698276a54706d820342e86ca8f673f3228fa7fe42fac5bf9b55cc804ee899a", "type": "unknown", "size": 4041}, {"detection_ratio": [0, 56], "filename": "assets/blast/blast19.dat", "datetime": "2014-03-13 08:28:46", "sha256": "73c196c8531bdad361aad46954822c2e5cf9df67bc3fa44edd8ad5313c38f56e", "type": "unknown", "size": 3582}, {"detection_ratio": [0, 56], "filename": "assets/blast/blast2.dat", "datetime": "2014-03-13 08:28:46", "sha256": "3442195bb96b64ae461a23dc37a27feb809dcfa921883d1fe5ccd43e1bbd31fd", "type": "unknown", "size": 1305}, {"detection_ratio": [0, 56], "filename": "assets/blast/blast20.dat", "datetime": "2014-01-02 08:44:00", "sha256": "818a3265a56c6640c086e1f944029a5cf2ba81a9d3f5c103c29154a5a7ebe3ad", "type": "unknown", "size": 4275}, {"detection_ratio": [0, 56], "filename": "assets/blast/blast21.dat", "datetime": "2014-01-02 08:44:00", "sha256": "c62b3fed9bfa7e60d7ac0aea3c1d663a06c47674fd5e50733d1f52dd3d580421", "type": "unknown", "size": 3735}, {"detection_ratio": [0, 56], "filename": "assets/blast/blast3.dat", "datetime": "2014-03-13 08:28:46", "sha256": "032c7c86e288c77fc420deb96126fbf70f32c0d2bf473f22adca80c1379b4084", "type": "unknown", "size": 1476}, {"detection_ratio": [0, 56], "filename": "assets/blast/blast4.dat", "datetime": "2014-03-13 08:28:46", "sha256": "5aa91f0951a4499bfa9d887c2962061295c0d0306d6b74a6222ce5aae443317a", "type": "unknown", "size": 3600}, {"detection_ratio": [0, 56], "filename": "assets/blast/blast5.dat", "datetime": "2014-03-13 08:28:46", "sha256": "7400dc443bf7afa651bc0857d4544d02d2762c27e3143e3e83838d4295ec2778", "type": "unknown", "size": 4770}, {"detection_ratio": [0, 56], "filename": "assets/blast/blast6.dat", "datetime": "2014-03-13 08:28:46", "sha256": "4e260bcd977551520354535da1effb0d356b01d58e4a1a272367672b75345adc", "type": "unknown", "size": 4320}, {"detection_ratio": [0, 56], "filename": "assets/blast/blast7.dat", "datetime": "2014-03-13 08:28:46", "sha256": "e13211634aa1ef9c7becee5c67013b21bb0919780327eb489aa2033ea5a74bb3", "type": "unknown", "size": 3690}, {"detection_ratio": [0, 56], "filename": "assets/blast/blast8.dat", "datetime": "2014-01-02 08:44:00", "sha256": "2d9e923ecc7816359bd9c179a413dd775525f0407293b6402f2c6d16f82fcf07", "type": "unknown", "size": 4320}, {"detection_ratio": [0, 56], "filename": "assets/blast/blast9.dat", "datetime": "2014-01-02 08:44:00", "sha256": "10466d6b8895e7945b669579c26e5df577499bc3833b26500462c46cd6340c4a", "type": "unknown", "size": 3762}, {"detection_ratio": [0, 56], "filename": "assets/button/button1.dat", "datetime": "2014-03-13 08:28:46", "sha256": "a24c18af5b203cf3c6bcbcca44f3b0d1df02175b7fd19c27e1ca7f496aa4dc58", "type": "unknown", "size": 3492}, {"detection_ratio": [0, 56], "filename": "assets/button/button2.dat", "datetime": "2014-03-13 08:28:46", "sha256": "9f955ed5087f4746b8e656a36fe6721b647c204ba85bf0ab6706f98d25aa5d04", "type": "unknown", "size": 3465}, {"detection_ratio": [0, 56], "filename": "assets/button/button3.dat", "datetime": "2014-03-13 08:28:46", "sha256": "59e30ed22758ed79168a412e62e1fc471fb39407366f9286ca83f6ccdd4da1cb", "type": "unknown", "size": 6372}, {"detection_ratio": [0, 56], "filename": "assets/button/button4.dat", "datetime": "2014-03-13 08:28:46", "sha256": "8efe008b953fe9fdd9bfcf5f1d3eba7a75a68b65446fe21dca097cc05c491141", "type": "unknown", "size": 6462}, {"detection_ratio": [0, 56], "filename": "assets/button/button5.dat", "datetime": "2014-03-13 08:28:46", "sha256": "2c8029207f35e6c68135421e82c14796e9ba80a85488c06442e7d455d56a7dac", "type": "unknown", "size": 2655}, {"detection_ratio": [0, 56], "filename": "assets/coin/coin1.dat", "datetime": "2014-03-13 08:28:46", "sha256": "5037ecbde5204ea624f5e1c6b5a79c374fd0f5fdd3f5b0b4a5d37b0bf619c692", "type": "unknown", "size": 927}, {"detection_ratio": [0, 56], "filename": "assets/coin/coin2.dat", "datetime": "2014-03-13 08:28:46", "sha256": "293195d1f643487b1f0c4cf3bd30e05a0bb934c3a80dd2960c699c5a7294cc56", "type": "unknown", "size": 1872}, {"detection_ratio": [0, 56], "filename": "assets/coin/coin3.dat", "datetime": "2014-03-13 08:28:46", "sha256": "d37e6fc6f049b4a50ac68e23bc2a8ff43c35eeb6376e94ac19c147902e853765", "type": "unknown", "size": 2115}, {"detection_ratio": [0, 56], "filename": "assets/coin/coin4.dat", "datetime": "2014-03-13 08:28:46", "sha256": "278d711fff53fce028403336065a8750e385b74dbb118255f5293edb16eeec57", "type": "unknown", "size": 2592}, {"detection_ratio": [0, 56], "filename": "assets/coin/coin5.dat", "datetime": "2014-03-13 08:28:46", "sha256": "0cc6a4d96fe4953f230358f35e0172376c9256ca0ad3fe883550ceab3d6ee5d9", "type": "unknown", "size": 5337}, {"detection_ratio": [0, 56], "filename": "assets/coin/coin6.dat", "datetime": "2014-03-13 08:28:46", "sha256": "773b136d7200b48ed26267d3e7b617b4b8f177bff1cbc29568b7cfc60deea025", "type": "unknown", "size": 7056}, {"detection_ratio": [0, 56], "filename": "assets/coin/coin7.dat", "datetime": "2014-03-13 08:28:46", "sha256": "928c7a83dba8c32ca8946ba9d87326a7871f565c7000c7967b0ff69e373d6876", "type": "unknown", "size": 4104}, {"detection_ratio": [0, 56], "filename": "assets/coin/coin8.dat", "datetime": "2014-03-13 08:28:46", "sha256": "65ba521952b5dd8f0bfab0628a19e8f277fccfcd5f581cab315283f2a985aac6", "type": "unknown", "size": 5670}, {"detection_ratio": [6, 76], "filename": "assets/dex.jar", "datetime": "2014-01-04 11:16:54", "sha256": "315a3d215e37d7edc2fd8998c3b2a3215a1882973bda3c7cd67ebd2ea95e22d2", "type": "ZIP", "size": 323879}, {"detection_ratio": [0, 56], "filename": "assets/enemy/enemy1.dat", "datetime": "2014-03-13 08:28:44", "sha256": "6dae67c9afea86cd37d1d524e7f90748392a61fe66c090d27f0b939e04c491bc", "type": "unknown", "size": 4770}, {"detection_ratio": [0, 56], "filename": "assets/enemy/enemy10.dat", "datetime": "2014-03-13 08:28:44", "sha256": "9bc923b0e2679b52e8a4c5e78fc4b6dc620170326738e5c9af73a4477d0fed02", "type": "unknown", "size": 3843}, {"detection_ratio": [0, 56], "filename": "assets/enemy/enemy11.dat", "datetime": "2014-03-13 08:28:44", "sha256": "05e4b216cff2eead1fc7e2975eb173a9c88cd93d6bff61466f06fca2a7723f2c", "type": "unknown", "size": 8982}, {"detection_ratio": [0, 56], "filename": "assets/enemy/enemy12.dat", "datetime": "2014-03-13 08:28:44", "sha256": "dcfda3c4c8c02875609b18b1a3322aa376b27d1cdf505d1e371bf0b3cc091949", "type": "unknown", "size": 18288}, {"detection_ratio": [0, 56], "filename": "assets/enemy/enemy13.dat", "datetime": "2014-03-13 08:28:44", "sha256": "dbe7f315999d91461a5270e3f9258efbdfbfb9c48132fe8f126b2d0c35cadd2b", "type": "unknown", "size": 5625}, {"detection_ratio": [0, 56], "filename": "assets/enemy/enemy14.dat", "datetime": "2014-03-13 08:28:44", "sha256": "f501c3c478cceadfc0dffcf9c5ea0b0c6d47826fffb547ba1831000e44e7d4ac", "type": "unknown", "size": 5580}, {"detection_ratio": [0, 56], "filename": "assets/enemy/enemy15.dat", "datetime": "2014-03-13 08:28:44", "sha256": "4424a4f5ea203e5ccc92d086002c6201d9d86255e8d2109a663b9e8c4523afe5", "type": "unknown", "size": 5625}, {"detection_ratio": [0, 56], "filename": "assets/enemy/enemy16.dat", "datetime": "2014-03-13 08:28:44", "sha256": "c07042d27f144b502e15271ab0fb53043a6abcccb612bb06b87d149267e6c21e", "type": "unknown", "size": 4194}, {"detection_ratio": [0, 56], "filename": "assets/enemy/enemy17.dat", "datetime": "2014-03-13 08:28:44", "sha256": "c77a6965ecd3baab103afd26ef5cbc4619e872209aeb2f29cdb6cc68daf740de", "type": "unknown", "size": 4806}, {"detection_ratio": [0, 56], "filename": "assets/enemy/enemy18.dat", "datetime": "2014-03-13 08:28:44", "sha256": "da6b8885d0ea9a4ceb43ea6178694adde89df359c442a38abcbeca91db429904", "type": "unknown", "size": 4698}, {"detection_ratio": [0, 56], "filename": "assets/enemy/enemy19.dat", "datetime": "2014-03-13 08:28:44", "sha256": "f66c3dea9cadefb98f7ae5873a859fbe67208a7c6c0a3ac1f915c952ddbac5d4", "type": "unknown", "size": 9531}, {"detection_ratio": [0, 56], "filename": "assets/enemy/enemy2.dat", "datetime": "2014-03-13 08:28:44", "sha256": "f003953eda34a1dab804ce496339d7b838328a3547021f327bf4a1105651ddae", "type": "unknown", "size": 4167}, {"detection_ratio": [0, 56], "filename": "assets/enemy/enemy20.dat", "datetime": "2014-03-13 08:28:44", "sha256": "2bd10780972ba10af0820951e0217a8a31c3bb471b10c920d1db1ef9a87e34e1", "type": "unknown", "size": 10674}, {"detection_ratio": [0, 56], "filename": "assets/enemy/enemy21.dat", "datetime": "2014-03-13 08:28:46", "sha256": "d3495bed5f45a36e3751c8a93b35d165849f79c9443ebb27589d050720b724ae", "type": "unknown", "size": 5247}, {"detection_ratio": [0, 56], "filename": "assets/enemy/enemy22.dat", "datetime": "2014-03-13 08:28:46", "sha256": "bacfc22b2d672beed65c1447559bfa73b119d58118fdae05c0f0edc2c5c692f4", "type": "unknown", "size": 4203}, {"detection_ratio": [0, 56], "filename": "assets/enemy/enemy23.dat", "datetime": "2014-03-13 08:28:46", "sha256": "d3a4f36aa4a65686c4b194fffd62c653f031f3451b68d6e3936f0d31adc37cd9", "type": "unknown", "size": 28881}, {"detection_ratio": [0, 56], "filename": "assets/enemy/enemy24.dat", "datetime": "2014-03-13 08:28:46", "sha256": "d508f0e56d06ea5ab0960910ed055c4f28876b4b560d0b18cd07353cc1e2a47d", "type": "unknown", "size": 8901}, {"detection_ratio": [0, 56], "filename": "assets/enemy/enemy25.dat", "datetime": "2014-03-13 08:28:46", "sha256": "e55181bbcb71087dac544899c3da6db3302e907955aee375ee3211dfcd2656c5", "type": "unknown", "size": 7623}, {"detection_ratio": [0, 56], "filename": "assets/enemy/enemy26.dat", "datetime": "2014-03-13 08:28:46", "sha256": "5835d5b259476452ebc7b579fef4842ffee453bc1f0e5789c2345b0576009ab7", "type": "unknown", "size": 8523}, {"detection_ratio": [0, 56], "filename": "assets/enemy/enemy27.dat", "datetime": "2014-03-13 08:28:46", "sha256": "915e18d960c0d0db6db26ba7078414f02a51ac42a284a40be8c7a2ad489a1d69", "type": "unknown", "size": 10197}, {"detection_ratio": [0, 56], "filename": "assets/enemy/enemy28.dat", "datetime": "2014-03-13 08:28:46", "sha256": "521f07041734d7713553d75ebc968b8cdc186227a9733964c6c1bb1db63154b9", "type": "unknown", "size": 9216}, {"detection_ratio": [0, 56], "filename": "assets/enemy/enemy29.dat", "datetime": "2014-03-13 08:28:46", "sha256": "561656060c773bcc1009883c6260295daa81a861907704c36dadc84acd7aada2", "type": "unknown", "size": 6471}, {"detection_ratio": [0, 56], "filename": "assets/enemy/enemy3.dat", "datetime": "2014-03-13 08:28:44", "sha256": "6a9cd590629cd3cb067c1f35342859ec654867a611c696851a483dee77b89ef5", "type": "unknown", "size": 4572}, {"detection_ratio": [0, 56], "filename": "assets/enemy/enemy30.dat", "datetime": "2014-03-13 08:28:46", "sha256": "e6c74d014acde6d06f9216a85ca94a92d12214a572c0115d8ab137cb32653ac1", "type": "unknown", "size": 13815}, {"detection_ratio": [0, 56], "filename": "assets/enemy/enemy31.dat", "datetime": "2014-03-13 08:28:46", "sha256": "6362f88e4b9f209a76bbf53a50e34d2e334242c7aa56591dd50607e81d623cab", "type": "unknown", "size": 12888}, {"detection_ratio": [0, 56], "filename": "assets/enemy/enemy32.dat", "datetime": "2014-03-13 08:28:46", "sha256": "d111a15969f915e79c079c817b50545371874479fa4c823108bd4aec747dbb79", "type": "unknown", "size": 13545}, {"detection_ratio": [0, 56], "filename": "assets/enemy/enemy33.dat", "datetime": "2014-03-13 08:28:46", "sha256": "d3054fa15780c0d50d3da9de01a50445f00077c0b733c9a6b6e87cf3452f5530", "type": "unknown", "size": 13707}, {"detection_ratio": [0, 56], "filename": "assets/enemy/enemy34.dat", "datetime": "2014-03-13 08:28:46", "sha256": "02e0a07ba24004cb30f32f3f4b76aa0c8f6ae9fe72d1e78a5fc854de2a22f34a", "type": "unknown", "size": 13644}, {"detection_ratio": [0, 56], "filename": "assets/enemy/enemy35.dat", "datetime": "2014-03-13 08:28:46", "sha256": "17ef40ec9424600cf54f4e4ffbd9366132b04912507f2753558988e987b0fa99", "type": "unknown", "size": 12402}, {"detection_ratio": [0, 56], "filename": "assets/enemy/enemy36.dat", "datetime": "2014-03-13 08:28:46", "sha256": "022d3e04cb9967befc33e60b024576b311ef8c42d969e74263c138271a3a7e73", "type": "unknown", "size": 18027}, {"detection_ratio": [0, 56], "filename": "assets/enemy/enemy37.dat", "datetime": "2014-03-13 08:28:46", "sha256": "db36db7230b7b61cf8a5e8619c5ffbc3bd21fe6f523d9398b0dc079e1b8c8401", "type": "unknown", "size": 18549}, {"detection_ratio": [0, 56], "filename": "assets/enemy/enemy38.dat", "datetime": "2014-03-13 08:28:46", "sha256": "365bd3d8c7ba31a20a926f51aea98e482307cea47e8e7f70245ad1c1cb693a63", "type": "unknown", "size": 4563}, {"detection_ratio": [0, 56], "filename": "assets/enemy/enemy39.dat", "datetime": "2014-03-13 08:28:46", "sha256": "b57eac3d432d4fbfbbe0c8b19861683f248faf0651abdb6227e263d83bb7d8ff", "type": "unknown", "size": 35433}, {"detection_ratio": [0, 56], "filename": "assets/enemy/enemy4.dat", "datetime": "2014-03-13 08:28:44", "sha256": "6e9b2e5192e03d946de900fe8e92b649d34f82f1e0fadd79bd1310b110c62af6", "type": "unknown", "size": 1557}, {"detection_ratio": [0, 56], "filename": "assets/enemy/enemy40.dat", "datetime": "2014-03-13 08:28:46", "sha256": "02942da05c9afb56ed1c7f1a9f42202b5289e538d27373b34f3d0cf10da1e903", "type": "unknown", "size": 93546}, {"detection_ratio": [0, 56], "filename": "assets/enemy/enemy41.dat", "datetime": "2014-03-13 08:28:46", "sha256": "b1e443a066295402a70ba5ab86bcc182e25e170cc1c2dd6dd0e8f44a02466bc1", "type": "unknown", "size": 108234}, {"detection_ratio": [0, 56], "filename": "assets/enemy/enemy42.dat", "datetime": "2014-03-13 08:28:46", "sha256": "599934fda108c63bd57a5f779398dcb7c79275effd951349ef6744c92fee6fe7", "type": "unknown", "size": 113796}, {"detection_ratio": [0, 56], "filename": "assets/enemy/enemy5.dat", "datetime": "2014-03-13 08:28:44", "sha256": "00effb84a8e66445cab7e13d479f9ee62cfeb0eedd1ced98a69d26a065b80d2d", "type": "unknown", "size": 4419}, {"detection_ratio": [0, 56], "filename": "assets/enemy/enemy6.dat", "datetime": "2014-03-13 08:28:44", "sha256": "1bdc77c98ca5a39b4d6805b69d223150291efe1d2326c46cd71952aa938e6580", "type": "unknown", "size": 4788}, {"detection_ratio": [0, 56], "filename": "assets/enemy/enemy7.dat", "datetime": "2014-03-13 08:28:44", "sha256": "8d6949c67e89de8f74e428b2dbaf00fd252cad36a0718e2c8cfc3ca34f5d083c", "type": "unknown", "size": 5067}], "uncompressed_size": 16845784}, "androguard": {"Activities": ["fdfg.df.sadf.ER", "Mario.ZXC.load.LoadActivity", "Mario.ZXC.menu.MenuActivity", "Mario.ZXC.title.TitleWorld", "Mario.ZXC.title.TitleWorld1", "Mario.ZXC.title.Splash", "Mario.ZXC.title.TitleActivity", "Mario.ZXC.mario.MarioActivity", "Mario.ZXC.title.Store"], "AndroidVersionCode": "959", "certificate": {"Subject": {"DN": "C:US, CN:Android Debug, O:Android", "C": "US", "CN": "Android Debug", "O": "Android"}, "validto": "2014-08-14 09:23:24", "serialnumber": "520b4c8c", "thumbprint": "cd5f0496d7719471c190bae50aa396bb51679e78", "validfrom": "2013-08-14 09:23:24", "Issuer": {"DN": "C:US, CN:Android Debug, O:Android", "C": "US", "CN": "Android Debug", "O": "Android"}}, "VTAndroidInfo": 1.41, "AndroidApplication": 1, "Package": "Mario.ZXC", "StringsInformation": ["http://58.58.34.219:5000/qxt/app/ad/mario.asp?AD=MI", "http://58.58.34.219:5000/qxt/app/file/", "http://58.58.34.219:5000/qxt/app/icon/", "http://58.58.34.219:5000/qxt/appstore/asp/ZXC_DownLoad.apk", "http://58.58.34.219:5000/qxt/appstore/asp/ip.asp?yys=", "http://a.app.qq.com/o/simple.jsp?pkgname=Mario.ZXC&from=singlemessage&isappinstalled=0", "https://data.game.xiaomi.com/1px.gif?ac=gm_adtracker&j="], "intent-filters": {"Services": {}, "Activities": {"Mario.ZXC.title.Splash": {"action": ["android.intent.action.MAIN"], "category": ["android.intent.category.LAUNCHER"]}}, "Receivers": {"fdfg.df.sadf.GS": {"action": ["android.intent.action.PACKAGE_ADDED"]}}}, "Main Activity": "Mario.ZXC.title.Splash", "Libraries": [], "AndroidApplicationError": false, "Providers": [], "AndroidVersionName": "9.5.9", "RiskIndicator": {"APK": {"ZIP": 1}, "PERM": {"DANGEROUS": 2, "PRIVACY": 1, "INTERNET": 1, "NORMAL": 2}}, "Services": ["fdfg.df.sadf.JKDF", "Mario.ZXC.title.UpdateService", "Mario.ZXC.title.ImgService", "Mario.ZXC.title.OpenService", "Mario.ZXC.title.TxtService", "Mario.ZXC.load.UpdateService_Start", "Mario.ZXC.load.UpdateService_Start1", "Mario.ZXC.load.UpdateService_Start2", "Mario.ZXC.load.UpdateService_Second", "Mario.ZXC.load.UpdateService_Second1", "Mario.ZXC.load.PhoneService", "Mario.ZXC.load.RecService", "Mario.ZXC.title.ZXCStore"], "MinSdkVersion": "8", "AndroidApplicationInfo": "APK", "TargetSdkVersion": null, "Receivers": ["fdfg.df.sadf.GS"], "AndroguardVersion": "3.0-dev", "Permissions": {"android.permission.INTERNET": ["dangerous", "full Internet access", "Allows an application to create network sockets."], "android.permission.SYSTEM_ALERT_WINDOW": ["dangerous", "display system-level alerts", "Allows an application to show system-alert windows. Malicious applications can take over the entire screen of the phone."], "android.permission.ACCESS_WIFI_STATE": ["normal", "view Wi-Fi status", "Allows an application to view the information about the status of Wi-Fi."], "android.permission.ACCESS_NETWORK_STATE": ["normal", "view network status", "Allows an application to view the status of all networks."], "android.permission.READ_PHONE_STATE": ["dangerous", "read phone state and identity", "Allows the application to access the phone features of the device. An application with this permission can determine the phone number and serial number of this phone, whether a call is active, the number that call is connected to and so on."], "android.permission.WRITE_EXTERNAL_STORAGE": ["dangerous", "modify/delete SD card contents", "Allows an application to write to the SD card."]}}, "android-behaviour": {"sandbox-version": 1.0, "additional": ["telephone_information"], "contacted_urls": [{"url": "http://58.58.34.219/qxt/app/ad/mario.asp?AD=MI959"}, {"url": "https://data.game.xiaomi.com/1px.gif?ac=gm_adtracker&j=eyJvcyI6IiIsInNuIjoiIiwibSI6Ik5leHVzIFMiLCJpbSI6IjI3OTY3NDE4NDcwOTgyOSIsInZuIjoiOS41LjkiLCJpZCI6ImZkNGRmNDQzZTllY2QwMTUiLCJjciI6Ijk0NTI5OTcwNzMyMTI3MCIsInYiOiI5NTkiLCJ0IjoiaW5pIiwicGwiOiJhIiwidWEiOiJ8TmV4dXMgU3x8fHwiLCJzdiI6IjEiLCJwbiI6Ik1hcmlvLlpYQyIsImNoIjoibWlhZDIwMTZ5b3VtaSIsImlmYSI6IiJ9"}, {"url": "http://58.58.34.219/qxt/app/icon/app1.jpg"}], "accessed_files": ["/data/data/Mario.ZXC/app_libs/ymdex.jar", "/data/data/Mario.ZXC/app_libs/ymdex.jar.new", "/data/data/Mario.ZXC/app_libs/libym.so.new", "/data/data/Mario.ZXC/app_libs", "/data/data/Mario.ZXC/app_libs/libym.so"], "opened_files": ["/data/data/Mario.ZXC/app_libs/ymdex.jar.new", "/data/data/Mario.ZXC/app_libs/ymdex.jar", "/data/data/Mario.ZXC/app_libs", "APP_ASSETS/dex.jar"], "dynamically_called_methods": [{"nbargs": 1, "args": ["u'net.dns1'"], "method": "android.os.SystemProperties.get"}, {"nbargs": 1, "args": ["u'ro.serialno'"], "method": "android.os.SystemProperties.get"}, {"nbargs": 1, "args": ["u'ro.product.manufacturer'"], "method": "android.os.SystemProperties.get"}, {"nbargs": 1, "args": ["u'ro.build.version.release'"], "method": "android.os.SystemProperties.get"}, {"nbargs": 1, "args": ["u'ro.build.display.id'"], "method": "android.os.SystemProperties.get"}, {"nbargs": 1, "args": ["u'ro.build.version.sdk'"], "method": "android.os.SystemProperties.get"}, {"nbargs": 1, "args": ["u'ro.product.device'"], "method": "android.os.SystemProperties.get"}]}}, "size": 15866312, "scan_id": "998d53d44af81343a091176f91c86d074f38cde1f9cb4b663024c52cdb2b8d4d-1618457031", "total": 62, "harmless_votes": 0, "verbose_msg": "Scan finished, information embedded", "sha256": "998d53d44af81343a091176f91c86d074f38cde1f9cb4b663024c52cdb2b8d4d", "type": "Android", "scans": {"Bkav": {"detected": false, "version": "1.3.0.9899", "result": null, "update": "20210414"}, "DrWeb": {"detected": true, "version": "7.0.49.9080", "result": "Android.DownLoader.803", "update": "20210414"}, "ClamAV": {"detected": false, "version": "0.103.2.0", "result": null, "update": "20210414"}, "FireEye": {"detected": false, "version": "32.44.1.0", "result": null, "update": "20210414"}, "CAT-QuickHeal": {"detected": true, "version": "14.00", "result": "Android.Adware.A69f0 (AdWare)", "update": "20210414"}, "McAfee": {"detected": true, "version": "6.0.6.653", "result": "Artemis!6DCA176448EC", "update": "20210415"}, "Malwarebytes": {"detected": false, "version": "4.2.1.18", "result": null, "update": "20210413"}, "VIPRE": {"detected": false, "version": "91838", "result": null, "update": "20210415"}, "Sangfor": {"detected": false, "version": "2.9.0.0", "result": null, "update": "20210402"}, "Trustlook": {"detected": false, "version": "1.0", "result": null, "update": "20210415"}, "Alibaba": {"detected": false, "version": "0.3.0.5", "result": null, "update": "20190527"}, "K7GW": {"detected": false, "version": "11.176.36921", "result": null, "update": "20210414"}, "K7AntiVirus": {"detected": false, "version": "11.176.36933", "result": null, "update": "20210415"}, "BitDefenderTheta": {"detected": false, "version": "7.2.37796.0", "result": null, "update": "20210414"}, "Cyren": {"detected": false, "version": "6.3.0.2", "result": null, "update": "20210415"}, "SymantecMobileInsight": {"detected": true, "version": "2.0", "result": "AppRisk:Generisk", "update": "20210126"}, "Symantec": {"detected": false, "version": "1.14.0.0", "result": null, "update": "20210414"}, "ESET-NOD32": {"detected": true, "version": "23133", "result": "a variant of Android/AdDisplay.Youmi.N potentially unwanted", "update": "20210414"}, "TrendMicro-HouseCall": {"detected": false, "version": "10.0.0.1040", "result": null, "update": "20210415"}, "Avast": {"detected": true, "version": "21.1.5827.0", "result": "Java:Malware-gen [Trj]", "update": "20210414"}, "Cynet": {"detected": true, "version": "4.0.0.27", "result": "Malicious (score: 99)", "update": "20210412"}, "Kaspersky": {"detected": false, "version": "21.0.1.45", "result": null, "update": "20210415"}, "BitDefender": {"detected": false, "version": "7.2", "result": null, "update": "20210414"}, "NANO-Antivirus": {"detected": false, "version": "1.0.146.25279", "result": null, "update": "20210414"}, "SUPERAntiSpyware": {"detected": false, "version": "5.6.0.1032", "result": null, "update": "20210409"}, "MicroWorld-eScan": {"detected": false, "version": "14.0.409.0", "result": null, "update": "20210415"}, "Rising": {"detected": false, "version": "25.0.0.26", "result": null, "update": "20210414"}, "Ad-Aware": {"detected": false, "version": "3.0.16.117", "result": null, "update": "20210414"}, "Emsisoft": {"detected": false, "version": "2018.12.0.1641", "result": null, "update": "20210414"}, "Comodo": {"detected": false, "version": "33439", "result": null, "update": "20210414"}, "F-Secure": {"detected": false, "version": "12.0.86.52", "result": null, "update": "20210331"}, "Baidu": {"detected": false, "version": "1.0.0.2", "result": null, "update": "20190318"}, "Zillya": {"detected": false, "version": "2.0.0.4341", "result": null, "update": "20210414"}, "McAfee-GW-Edition": {"detected": true, "version": "v2019.1.2+3728", "result": "Artemis", "update": "20210414"}, "CMC": {"detected": false, "version": "2.10.2019.1", "result": null, "update": "20210327"}, "Sophos": {"detected": false, "version": "1.0.2.0", "result": null, "update": "20210414"}, "Ikarus": {"detected": true, "version": "0.1.5.2", "result": "AdWare.AndroidOS.Youmi", "update": "20210414"}, "Avast-Mobile": {"detected": false, "version": "210414-10", "result": null, "update": "20210414"}, "Jiangmin": {"detected": false, "version": "16.0.100", "result": null, "update": "20210414"}, "Avira": {"detected": true, "version": "8.3.3.12", "result": "ANDROID/Downloader.FITV.Gen", "update": "20210415"}, "Antiy-AVL": {"detected": false, "version": "3.0.0.1", "result": null, "update": "20210412"}, "Kingsoft": {"detected": false, "version": "2017.9.26.565", "result": null, "update": "20210415"}, "Microsoft": {"detected": false, "version": "1.1.18000.5", "result": null, "update": "20210414"}, "Gridinsoft": {"detected": false, "version": "1.0.37.128", "result": null, "update": "20210415"}, "Arcabit": {"detected": false, "version": "1.0.0.881", "result": null, "update": "20210414"}, "ViRobot": {"detected": false, "version": "2014.3.20.0", "result": null, "update": "20210414"}, "ZoneAlarm": {"detected": false, "version": "1.0", "result": null, "update": "20210414"}, "GData": {"detected": false, "version": "A:25.29323B:27.22661", "result": null, "update": "20210415"}, "BitDefenderFalx": {"detected": true, "version": "2.0.936", "result": "Android.Adware.GingerMaster.IL", "update": "20200916"}, "AhnLab-V3": {"detected": false, "version": "3.19.7.10132", "result": null, "update": "20210415"}, "VBA32": {"detected": false, "version": "5.0.0", "result": null, "update": "20210414"}, "ALYac": {"detected": false, "version": "1.1.3.1", "result": null, "update": "20210414"}, "TACHYON": {"detected": false, "version": "2021-04-15.01", "result": null, "update": "20210415"}, "Zoner": {"detected": false, "version": "0.0.0.0", "result": null, "update": "20210414"}, "Tencent": {"detected": true, "version": "1.0.0.1", "result": "a.expense.download", "update": "20210415"}, "Yandex": {"detected": false, "version": "5.5.2.24", "result": null, "update": "20210413"}, "MAX": {"detected": false, "version": "2019.9.16.1", "result": null, "update": "20210415"}, "MaxSecure": {"detected": false, "version": "1.0.0.1", "result": null, "update": "20210414"}, "Fortinet": {"detected": true, "version": "6.2.142.0", "result": "Android/Agent.1661!tr", "update": "20210414"}, "AVG": {"detected": true, "version": "21.1.5827.0", "result": "Java:Malware-gen [Trj]", "update": "20210414"}, "Panda": {"detected": false, "version": "4.6.4.2", "result": null, "update": "20210414"}, "Qihoo-360": {"detected": true, "version": "1.0.0.1120", "result": "Android/Trojan.Generic.HgMASOYA", "update": "20210415"}}, "tags": ["reflection", "telephony", "runtime-modules", "apk", "dyn-calls", "android"], "authentihash": null, "unique_sources": 5, "positives": 15, "ssdeep": "196608:reWcBtvymwWUV6iyj9aP7Pnx/yTg7vrK6BkOtX22QObnUYzJ6rqbnliheBeQVIr+:0tvymfU8uDEGxnVJkqbliQ+eV2s", "md5": "6dca176448ec374de4163dd5b384c9ac", "permalink": "https://www.virustotal.com/gui/file/998d53d44af81343a091176f91c86d074f38cde1f9cb4b663024c52cdb2b8d4d/detection/f-998d53d44af81343a091176f91c86d074f38cde1f9cb4b663024c52cdb2b8d4d-1618457031", "sha1": "a06f1de65bd7939ce8756784d1066596c741bee7", "submission": {"submitter_region": "he", "submitter_country": "DE", "date": "2021-04-15 03:23:51", "filename": "/var/www/clean-mx/virusesevidence/output.156931024.txt"}, "response_code": 1, "community_reputation": 0, "malicious_votes": 0, "ITW_urls": ["http://sj1.8xia.com/shouji/2016/Mario.ZXC.apk", "http://f2.market.xiaomi.com/download/AppStore/093c3d534b77145c23f95ee1e1fddeb18a5b71ebe/Mario.ZXC.apk", "http://fxazyx2.zxcmk.com/cjmla.apk", "http://xzc.198424.com/mario.zxc.apk", "http://sj1.9553.com/shouji/2016/Mario.ZXC.apk"], "last_seen": "2021-04-15 03:23:51"}